[
  {
    "year": 2007,
    "session": "Q",
    "driverId": "ALO",
    "lapTime": 84.806
  },
  {
    "year": 2007,
    "session": "Q",
    "driverId": "BAR",
    "lapTime": 87.323
  },
  {
    "year": 2007,
    "session": "Q",
    "driverId": "BUT",
    "lapTime": 85.454
  },
  {
    "year": 2007,
    "session": "Q",
    "driverId": "COU",
    "lapTime": 86.247
  },
  {
    "year": 2007,
    "session": "Q",
    "driverId": "DAV",
    "lapTime": 87.564
  },
  {
    "year": 2007,
    "session": "Q",
    "driverId": "FIS",
    "lapTime": 86.033
  },
  {
    "year": 2007,
    "session": "Q",
    "driverId": "HAM",
    "lapTime": 84.753
  },
  {
    "year": 2007,
    "session": "Q",
    "driverId": "HEI",
    "lapTime": 85.248
  },
  {
    "year": 2007,
    "session": "Q",
    "driverId": "KOV",
    "lapTime": 86.232
  },
  {
    "year": 2007,
    "session": "Q",
    "driverId": "KUB",
    "lapTime": 85.53
  },
  {
    "year": 2007,
    "session": "Q",
    "driverId": "LIU",
    "lapTime": 86.948
  },
  {
    "year": 2007,
    "session": "Q",
    "driverId": "MAS",
    "lapTime": 85.049
  },
  {
    "year": 2007,
    "session": "Q",
    "driverId": "RAI",
    "lapTime": 84.988
  },
  {
    "year": 2007,
    "session": "Q",
    "driverId": "ROS",
    "lapTime": 85.816
  },
  {
    "year": 2007,
    "session": "Q",
    "driverId": "SAT",
    "lapTime": 88.762
  },
  {
    "year": 2007,
    "session": "Q",
    "driverId": "SCH",
    "lapTime": 87.191
  },
  {
    "year": 2007,
    "session": "Q",
    "driverId": "SUT",
    "lapTime": 88.628
  },
  {
    "year": 2007,
    "session": "Q",
    "driverId": "TRU",
    "lapTime": 86.253
  },
  {
    "year": 2007,
    "session": "Q",
    "driverId": "VET",
    "lapTime": 85.909
  },
  {
    "year": 2007,
    "session": "Q",
    "driverId": "WEB",
    "lapTime": 85.535
  },
  {
    "year": 2007,
    "session": "Q",
    "driverId": "WUR",
    "lapTime": 87.454
  },
  {
    "year": 2007,
    "session": "Q",
    "driverId": "YAM",
    "lapTime": 89.668
  },
  {
    "year": 2007,
    "session": "R",
    "driverId": "ALO",
    "lapTime": 88.511
  },
  {
    "year": 2007,
    "session": "R",
    "driverId": "BAR",
    "lapTime": 91.06
  },
  {
    "year": 2007,
    "session": "R",
    "driverId": "BUT",
    "lapTime": 91.951
  },
  {
    "year": 2007,
    "session": "R",
    "driverId": "COU",
    "lapTime": 90.086
  },
  {
    "year": 2007,
    "session": "R",
    "driverId": "DAV",
    "lapTime": 91.803
  },
  {
    "year": 2007,
    "session": "R",
    "driverId": "FIS",
    "lapTime": 90.387
  },
  {
    "year": 2007,
    "session": "R",
    "driverId": "HAM",
    "lapTime": 88.193
  },
  {
    "year": 2007,
    "session": "R",
    "driverId": "HEI",
    "lapTime": 89.084
  },
  {
    "year": 2007,
    "session": "R",
    "driverId": "KOV",
    "lapTime": 89.655
  },
  {
    "year": 2007,
    "session": "R",
    "driverId": "KUB",
    "lapTime": 89.021
  },
  {
    "year": 2007,
    "session": "R",
    "driverId": "LIU",
    "lapTime": 90.653
  },
  {
    "year": 2007,
    "session": "R",
    "driverId": "MAS",
    "lapTime": 89.588
  },
  {
    "year": 2007,
    "session": "R",
    "driverId": "RAI",
    "lapTime": 89.619
  },
  {
    "year": 2007,
    "session": "R",
    "driverId": "ROS",
    "lapTime": 89.926
  },
  {
    "year": 2007,
    "session": "R",
    "driverId": "SAT",
    "lapTime": 91.507
  },
  {
    "year": 2007,
    "session": "R",
    "driverId": "SCH",
    "lapTime": 90.865
  },
  {
    "year": 2007,
    "session": "R",
    "driverId": "SUT",
    "lapTime": 91.891
  },
  {
    "year": 2007,
    "session": "R",
    "driverId": "TRU",
    "lapTime": 92.414
  },
  {
    "year": 2007,
    "session": "R",
    "driverId": "VET",
    "lapTime": 89.057
  },
  {
    "year": 2007,
    "session": "R",
    "driverId": "WEB",
    "lapTime": 88.94
  },
  {
    "year": 2007,
    "session": "R",
    "driverId": "WUR",
    "lapTime": 125.636
  },
  {
    "year": 2007,
    "session": "R",
    "driverId": "YAM",
    "lapTime": 92.13
  },
  {
    "year": 2008,
    "session": "Q",
    "driverId": "ALO",
    "lapTime": 77.871
  },
  {
    "year": 2008,
    "session": "Q",
    "driverId": "BAR",
    "lapTime": 78.882
  },
  {
    "year": 2008,
    "session": "Q",
    "driverId": "BOU",
    "lapTime": 78.102
  },
  {
    "year": 2008,
    "session": "Q",
    "driverId": "BUT",
    "lapTime": 79.1
  },
  {
    "year": 2008,
    "session": "Q",
    "driverId": "COU",
    "lapTime": 78.187
  },
  {
    "year": 2008,
    "session": "Q",
    "driverId": "FIS",
    "lapTime": 79.91
  },
  {
    "year": 2008,
    "session": "Q",
    "driverId": "GLO",
    "lapTime": 77.67
  },
  {
    "year": 2008,
    "session": "Q",
    "driverId": "HAM",
    "lapTime": 77.462
  },
  {
    "year": 2008,
    "session": "Q",
    "driverId": "HEI",
    "lapTime": 78.835
  },
  {
    "year": 2008,
    "session": "Q",
    "driverId": "KOV",
    "lapTime": 77.36
  },
  {
    "year": 2008,
    "session": "Q",
    "driverId": "KUB",
    "lapTime": 77.931
  },
  {
    "year": 2008,
    "session": "Q",
    "driverId": "MAS",
    "lapTime": 77.287
  },
  {
    "year": 2008,
    "session": "Q",
    "driverId": "NAK",
    "lapTime": 78.594
  },
  {
    "year": 2008,
    "session": "Q",
    "driverId": "PIQ",
    "lapTime": 78.274
  },
  {
    "year": 2008,
    "session": "Q",
    "driverId": "RAI",
    "lapTime": 77.733
  },
  {
    "year": 2008,
    "session": "Q",
    "driverId": "ROS",
    "lapTime": 78.672
  },
  {
    "year": 2008,
    "session": "Q",
    "driverId": "SUT",
    "lapTime": 79.163
  },
  {
    "year": 2008,
    "session": "Q",
    "driverId": "TRU",
    "lapTime": 77.541
  },
  {
    "year": 2008,
    "session": "Q",
    "driverId": "VET",
    "lapTime": 77.714
  },
  {
    "year": 2008,
    "session": "Q",
    "driverId": "WEB",
    "lapTime": 78.354
  },
  {
    "year": 2008,
    "session": "R",
    "driverId": "ALO",
    "lapTime": 79.101
  },
  {
    "year": 2008,
    "session": "R",
    "driverId": "BAR",
    "lapTime": 80.575
  },
  {
    "year": 2008,
    "session": "R",
    "driverId": "BOU",
    "lapTime": 79.262
  },
  {
    "year": 2008,
    "session": "R",
    "driverId": "BUT",
    "lapTime": 80.849
  },
  {
    "year": 2008,
    "session": "R",
    "driverId": "FIS",
    "lapTime": 81.577
  },
  {
    "year": 2008,
    "session": "R",
    "driverId": "GLO",
    "lapTime": 80.254
  },
  {
    "year": 2008,
    "session": "R",
    "driverId": "HAM",
    "lapTime": 79.56
  },
  {
    "year": 2008,
    "session": "R",
    "driverId": "HEI",
    "lapTime": 79.461
  },
  {
    "year": 2008,
    "session": "R",
    "driverId": "KOV",
    "lapTime": 79.258
  },
  {
    "year": 2008,
    "session": "R",
    "driverId": "KUB",
    "lapTime": 79.292
  },
  {
    "year": 2008,
    "session": "R",
    "driverId": "MAS",
    "lapTime": 78.426
  },
  {
    "year": 2008,
    "session": "R",
    "driverId": "NAK",
    "lapTime": 80.364
  },
  {
    "year": 2008,
    "session": "R",
    "driverId": "PIQ",
    "lapTime": 79.199
  },
  {
    "year": 2008,
    "session": "R",
    "driverId": "RAI",
    "lapTime": 78.995
  },
  {
    "year": 2008,
    "session": "R",
    "driverId": "ROS",
    "lapTime": 79.531
  },
  {
    "year": 2008,
    "session": "R",
    "driverId": "SUT",
    "lapTime": 81.189
  },
  {
    "year": 2008,
    "session": "R",
    "driverId": "TRU",
    "lapTime": 79.524
  },
  {
    "year": 2008,
    "session": "R",
    "driverId": "VET",
    "lapTime": 79.617
  },
  {
    "year": 2008,
    "session": "R",
    "driverId": "WEB",
    "lapTime": 79.82
  }
]