[
  {
    "year": 1994,
    "session": "Q",
    "driverId": "MSC",
    "lapTime": 81.885
  },
  {
    "year": 1994,
    "session": "Q",
    "driverId": "\\N",
    "lapTime": 81.548
  },
  {
    "year": 1995,
    "session": "Q",
    "driverId": "BAD",
    "lapTime": 93.071
  },
  {
    "year": 1995,
    "session": "Q",
    "driverId": "BAR",
    "lapTime": 89.551
  },
  {
    "year": 1995,
    "session": "Q",
    "driverId": "COU",
    "lapTime": 87.459
  },
  {
    "year": 1995,
    "session": "Q",
    "driverId": "MSC",
    "lapTime": 87.274
  },
  {
    "year": 1995,
    "session": "Q",
    "driverId": "\\N",
    "lapTime": 87.282
  },
  {
    "year": 1996,
    "session": "Q",
    "driverId": "BAD",
    "lapTime": 92.037
  },
  {
    "year": 1996,
    "session": "Q",
    "driverId": "BAR",
    "lapTime": 88.632
  },
  {
    "year": 1996,
    "session": "Q",
    "driverId": "COU",
    "lapTime": 87.688
  },
  {
    "year": 1996,
    "session": "Q",
    "driverId": "FIS",
    "lapTime": 90.814
  },
  {
    "year": 1996,
    "session": "Q",
    "driverId": "MSC",
    "lapTime": 86.89
  },
  {
    "year": 1996,
    "session": "Q",
    "driverId": "VIL",
    "lapTime": 87.22
  },
  {
    "year": 1996,
    "session": "Q",
    "driverId": "\\N",
    "lapTime": 87.105
  },
  {
    "year": 1997,
    "session": "Q",
    "driverId": "BAR",
    "lapTime": 85.579
  },
  {
    "year": 1997,
    "session": "Q",
    "driverId": "COU",
    "lapTime": 85.077
  },
  {
    "year": 1997,
    "session": "Q",
    "driverId": "FIS",
    "lapTime": 84.596
  },
  {
    "year": 1997,
    "session": "Q",
    "driverId": "MAG",
    "lapTime": 86.192
  },
  {
    "year": 1997,
    "session": "Q",
    "driverId": "MSC",
    "lapTime": 83.955
  },
  {
    "year": 1997,
    "session": "Q",
    "driverId": "SCH",
    "lapTime": 84.081
  },
  {
    "year": 1997,
    "session": "Q",
    "driverId": "TRU",
    "lapTime": 86.96
  },
  {
    "year": 1997,
    "session": "Q",
    "driverId": "VIL",
    "lapTime": 83.303
  },
  {
    "year": 1997,
    "session": "Q",
    "driverId": "\\N",
    "lapTime": 83.646
  },
  {
    "year": 1999,
    "session": "Q",
    "driverId": "BAD",
    "lapTime": 90.945
  },
  {
    "year": 1999,
    "session": "Q",
    "driverId": "BAR",
    "lapTime": 87.409
  },
  {
    "year": 1999,
    "session": "Q",
    "driverId": "COU",
    "lapTime": 86.384
  },
  {
    "year": 1999,
    "session": "Q",
    "driverId": "DLR",
    "lapTime": 89.293
  },
  {
    "year": 1999,
    "session": "Q",
    "driverId": "FIS",
    "lapTime": 88.75
  },
  {
    "year": 1999,
    "session": "Q",
    "driverId": "MSC",
    "lapTime": 86.538
  },
  {
    "year": 1999,
    "session": "Q",
    "driverId": "SCH",
    "lapTime": 87.77
  },
  {
    "year": 1999,
    "session": "Q",
    "driverId": "TRU",
    "lapTime": 88.403
  },
  {
    "year": 1999,
    "session": "Q",
    "driverId": "VIL",
    "lapTime": 87.313
  },
  {
    "year": 1999,
    "session": "Q",
    "driverId": "WUR",
    "lapTime": 88.765
  },
  {
    "year": 1999,
    "session": "Q",
    "driverId": "\\N",
    "lapTime": 86.362
  },
  {
    "year": 2000,
    "session": "Q",
    "driverId": "BAR",
    "lapTime": 85.871
  },
  {
    "year": 2000,
    "session": "Q",
    "driverId": "BUT",
    "lapTime": 87.135
  },
  {
    "year": 2000,
    "session": "Q",
    "driverId": "COU",
    "lapTime": 85.014
  },
  {
    "year": 2000,
    "session": "Q",
    "driverId": "DLR",
    "lapTime": 86.349
  },
  {
    "year": 2000,
    "session": "Q",
    "driverId": "FIS",
    "lapTime": 87.253
  },
  {
    "year": 2000,
    "session": "Q",
    "driverId": "HEI",
    "lapTime": 88.361
  },
  {
    "year": 2000,
    "session": "Q",
    "driverId": "MSC",
    "lapTime": 84.805
  },
  {
    "year": 2000,
    "session": "Q",
    "driverId": "SCH",
    "lapTime": 85.871
  },
  {
    "year": 2000,
    "session": "Q",
    "driverId": "TRU",
    "lapTime": 86.002
  },
  {
    "year": 2000,
    "session": "Q",
    "driverId": "VIL",
    "lapTime": 86.124
  },
  {
    "year": 2000,
    "session": "Q",
    "driverId": "WUR",
    "lapTime": 86.281
  },
  {
    "year": 2000,
    "session": "Q",
    "driverId": "ZON",
    "lapTime": 86.814
  },
  {
    "year": 2000,
    "session": "Q",
    "driverId": "\\N",
    "lapTime": 84.714
  },
  {
    "year": 2003,
    "session": "Q",
    "driverId": "ALO",
    "lapTime": 83.169
  },
  {
    "year": 2003,
    "session": "Q",
    "driverId": "BAR",
    "lapTime": 82.557
  },
  {
    "year": 2003,
    "session": "Q",
    "driverId": "BUT",
    "lapTime": 83.381
  },
  {
    "year": 2003,
    "session": "Q",
    "driverId": "COU",
    "lapTime": 83.818
  },
  {
    "year": 2003,
    "session": "Q",
    "driverId": "FIS",
    "lapTime": 84.317
  },
  {
    "year": 2003,
    "session": "Q",
    "driverId": "HEI",
    "lapTime": 83.7
  },
  {
    "year": 2003,
    "session": "Q",
    "driverId": "MON",
    "lapTime": 82.789
  },
  {
    "year": 2003,
    "session": "Q",
    "driverId": "MSC",
    "lapTime": 82.327
  },
  {
    "year": 2003,
    "session": "Q",
    "driverId": "PIZ",
    "lapTime": 84.147
  },
  {
    "year": 2003,
    "session": "Q",
    "driverId": "RAI",
    "lapTime": 83.148
  },
  {
    "year": 2003,
    "session": "Q",
    "driverId": "SCH",
    "lapTime": 82.341
  },
  {
    "year": 2003,
    "session": "Q",
    "driverId": "TRU",
    "lapTime": 84.19
  },
  {
    "year": 2003,
    "session": "Q",
    "driverId": "VIL",
    "lapTime": 83.16
  },
  {
    "year": 2003,
    "session": "Q",
    "driverId": "WEB",
    "lapTime": 83.015
  },
  {
    "year": 2003,
    "session": "Q",
    "driverId": "\\N",
    "lapTime": 83.46
  },
  {
    "year": 2004,
    "session": "Q",
    "driverId": "ALO",
    "lapTime": 80.895
  },
  {
    "year": 2004,
    "session": "Q",
    "driverId": "BAR",
    "lapTime": 80.451
  },
  {
    "year": 2004,
    "session": "Q",
    "driverId": "BUT",
    "lapTime": 79.753
  },
  {
    "year": 2004,
    "session": "Q",
    "driverId": "COU",
    "lapTime": 81.091
  },
  {
    "year": 2004,
    "session": "Q",
    "driverId": "HEI",
    "lapTime": 83.488
  },
  {
    "year": 2004,
    "session": "Q",
    "driverId": "KLI",
    "lapTime": 81.949
  },
  {
    "year": 2004,
    "session": "Q",
    "driverId": "MAS",
    "lapTime": 81.532
  },
  {
    "year": 2004,
    "session": "Q",
    "driverId": "MON",
    "lapTime": 80.212
  },
  {
    "year": 2004,
    "session": "Q",
    "driverId": "MSC",
    "lapTime": 80.011
  },
  {
    "year": 2004,
    "session": "Q",
    "driverId": "SAT",
    "lapTime": 80.913
  },
  {
    "year": 2004,
    "session": "Q",
    "driverId": "SCH",
    "lapTime": 80.538
  },
  {
    "year": 2004,
    "session": "Q",
    "driverId": "TRU",
    "lapTime": 81.034
  },
  {
    "year": 2004,
    "session": "Q",
    "driverId": "WEB",
    "lapTime": 80.921
  },
  {
    "year": 2004,
    "session": "Q",
    "driverId": "\\N",
    "lapTime": 81.087
  },
  {
    "year": 2004,
    "session": "R",
    "driverId": "ALO",
    "lapTime": 81.65
  },
  {
    "year": 2004,
    "session": "R",
    "driverId": "BAR",
    "lapTime": 81.873
  },
  {
    "year": 2004,
    "session": "R",
    "driverId": "BUT",
    "lapTime": 81.201
  },
  {
    "year": 2004,
    "session": "R",
    "driverId": "COU",
    "lapTime": 82.951
  },
  {
    "year": 2004,
    "session": "R",
    "driverId": "FIS",
    "lapTime": 82.654
  },
  {
    "year": 2004,
    "session": "R",
    "driverId": "HEI",
    "lapTime": 83.381
  },
  {
    "year": 2004,
    "session": "R",
    "driverId": "KLI",
    "lapTime": 83.647
  },
  {
    "year": 2004,
    "session": "R",
    "driverId": "MAS",
    "lapTime": 82.895
  },
  {
    "year": 2004,
    "session": "R",
    "driverId": "MON",
    "lapTime": 81.87
  },
  {
    "year": 2004,
    "session": "R",
    "driverId": "MSC",
    "lapTime": 80.411
  },
  {
    "year": 2004,
    "session": "R",
    "driverId": "RAI",
    "lapTime": 82.5
  },
  {
    "year": 2004,
    "session": "R",
    "driverId": "SAT",
    "lapTime": 81.929
  },
  {
    "year": 2004,
    "session": "R",
    "driverId": "SCH",
    "lapTime": 81.689
  },
  {
    "year": 2004,
    "session": "R",
    "driverId": "TRU",
    "lapTime": 81.666
  },
  {
    "year": 2004,
    "session": "R",
    "driverId": "WEB",
    "lapTime": 82.931
  },
  {
    "year": 2004,
    "session": "R",
    "driverId": "\\N",
    "lapTime": 82.861
  },
  {
    "year": 2005,
    "session": "Q",
    "driverId": "ALB",
    "lapTime": 85.921
  },
  {
    "year": 2005,
    "session": "Q",
    "driverId": "ALO",
    "lapTime": 79.889
  },
  {
    "year": 2005,
    "session": "Q",
    "driverId": "BAR",
    "lapTime": 80.892
  },
  {
    "year": 2005,
    "session": "Q",
    "driverId": "BUT",
    "lapTime": 80.464
  },
  {
    "year": 2005,
    "session": "Q",
    "driverId": "COU",
    "lapTime": 81.632
  },
  {
    "year": 2005,
    "session": "Q",
    "driverId": "FIS",
    "lapTime": 81.708
  },
  {
    "year": 2005,
    "session": "Q",
    "driverId": "FRI",
    "lapTime": 86.484
  },
  {
    "year": 2005,
    "session": "Q",
    "driverId": "HEI",
    "lapTime": 80.807
  },
  {
    "year": 2005,
    "session": "Q",
    "driverId": "KAR",
    "lapTime": 83.123
  },
  {
    "year": 2005,
    "session": "Q",
    "driverId": "LIU",
    "lapTime": 81.804
  },
  {
    "year": 2005,
    "session": "Q",
    "driverId": "MAS",
    "lapTime": 80.593
  },
  {
    "year": 2005,
    "session": "Q",
    "driverId": "MSC",
    "lapTime": 80.26
  },
  {
    "year": 2005,
    "session": "Q",
    "driverId": "RAI",
    "lapTime": 79.886
  },
  {
    "year": 2005,
    "session": "Q",
    "driverId": "SAT",
    "lapTime": 80.851
  },
  {
    "year": 2005,
    "session": "Q",
    "driverId": "SCH",
    "lapTime": 80.994
  },
  {
    "year": 2005,
    "session": "Q",
    "driverId": "TMO",
    "lapTime": 85.1
  },
  {
    "year": 2005,
    "session": "Q",
    "driverId": "TRU",
    "lapTime": 80.492
  },
  {
    "year": 2005,
    "session": "Q",
    "driverId": "VIL",
    "lapTime": 80.999
  },
  {
    "year": 2005,
    "session": "Q",
    "driverId": "WEB",
    "lapTime": 80.442
  },
  {
    "year": 2005,
    "session": "Q",
    "driverId": "WUR",
    "lapTime": 80.632
  },
  {
    "year": 2005,
    "session": "R",
    "driverId": "ALB",
    "lapTime": 87.42
  },
  {
    "year": 2005,
    "session": "R",
    "driverId": "ALO",
    "lapTime": 83.133
  },
  {
    "year": 2005,
    "session": "R",
    "driverId": "BAR",
    "lapTime": 84.435
  },
  {
    "year": 2005,
    "session": "R",
    "driverId": "BUT",
    "lapTime": 82.604
  },
  {
    "year": 2005,
    "session": "R",
    "driverId": "COU",
    "lapTime": 84.641
  },
  {
    "year": 2005,
    "session": "R",
    "driverId": "FIS",
    "lapTime": 85.665
  },
  {
    "year": 2005,
    "session": "R",
    "driverId": "FRI",
    "lapTime": 88.334
  },
  {
    "year": 2005,
    "session": "R",
    "driverId": "HEI",
    "lapTime": 83.917
  },
  {
    "year": 2005,
    "session": "R",
    "driverId": "KAR",
    "lapTime": 84.094
  },
  {
    "year": 2005,
    "session": "R",
    "driverId": "LIU",
    "lapTime": 83.488
  },
  {
    "year": 2005,
    "session": "R",
    "driverId": "MAS",
    "lapTime": 83.602
  },
  {
    "year": 2005,
    "session": "R",
    "driverId": "MSC",
    "lapTime": 81.858
  },
  {
    "year": 2005,
    "session": "R",
    "driverId": "RAI",
    "lapTime": 83.296
  },
  {
    "year": 2005,
    "session": "R",
    "driverId": "SAT",
    "lapTime": 83.368
  },
  {
    "year": 2005,
    "session": "R",
    "driverId": "SCH",
    "lapTime": 84.23
  },
  {
    "year": 2005,
    "session": "R",
    "driverId": "TMO",
    "lapTime": 84.719
  },
  {
    "year": 2005,
    "session": "R",
    "driverId": "TRU",
    "lapTime": 84.022
  },
  {
    "year": 2005,
    "session": "R",
    "driverId": "VIL",
    "lapTime": 84.017
  },
  {
    "year": 2005,
    "session": "R",
    "driverId": "WEB",
    "lapTime": 84.419
  },
  {
    "year": 2005,
    "session": "R",
    "driverId": "WUR",
    "lapTime": 83.023
  },
  {
    "year": 2006,
    "session": "Q",
    "driverId": "ALB",
    "lapTime": 87.088
  },
  {
    "year": 2006,
    "session": "Q",
    "driverId": "ALO",
    "lapTime": 83.536
  },
  {
    "year": 2006,
    "session": "Q",
    "driverId": "BAR",
    "lapTime": 83.242
  },
  {
    "year": 2006,
    "session": "Q",
    "driverId": "BUT",
    "lapTime": 82.988
  },
  {
    "year": 2006,
    "session": "Q",
    "driverId": "COU",
    "lapTime": 84.101
  },
  {
    "year": 2006,
    "session": "Q",
    "driverId": "FIS",
    "lapTime": 83.771
  },
  {
    "year": 2006,
    "session": "Q",
    "driverId": "HEI",
    "lapTime": 84.129
  },
  {
    "year": 2006,
    "session": "Q",
    "driverId": "IDE",
    "lapTime": 89.282
  },
  {
    "year": 2006,
    "session": "Q",
    "driverId": "KLI",
    "lapTime": 85.41
  },
  {
    "year": 2006,
    "session": "Q",
    "driverId": "LIU",
    "lapTime": 84.52
  },
  {
    "year": 2006,
    "session": "Q",
    "driverId": "MAS",
    "lapTime": 83.595
  },
  {
    "year": 2006,
    "session": "Q",
    "driverId": "MON",
    "lapTime": 83.76
  },
  {
    "year": 2006,
    "session": "Q",
    "driverId": "MSC",
    "lapTime": 82.579
  },
  {
    "year": 2006,
    "session": "Q",
    "driverId": "RAI",
    "lapTime": 83.19
  },
  {
    "year": 2006,
    "session": "Q",
    "driverId": "ROS",
    "lapTime": 83.966
  },
  {
    "year": 2006,
    "session": "Q",
    "driverId": "SAT",
    "lapTime": 87.609
  },
  {
    "year": 2006,
    "session": "Q",
    "driverId": "SCH",
    "lapTime": 83.565
  },
  {
    "year": 2006,
    "session": "Q",
    "driverId": "SPE",
    "lapTime": 85.437
  },
  {
    "year": 2006,
    "session": "Q",
    "driverId": "TMO",
    "lapTime": 86.82
  },
  {
    "year": 2006,
    "session": "Q",
    "driverId": "TRU",
    "lapTime": 83.727
  },
  {
    "year": 2006,
    "session": "Q",
    "driverId": "VIL",
    "lapTime": 83.887
  },
  {
    "year": 2006,
    "session": "Q",
    "driverId": "WEB",
    "lapTime": 83.718
  },
  {
    "year": 2006,
    "session": "R",
    "driverId": "ALO",
    "lapTime": 84.569
  },
  {
    "year": 2006,
    "session": "R",
    "driverId": "BAR",
    "lapTime": 86.129
  },
  {
    "year": 2006,
    "session": "R",
    "driverId": "BUT",
    "lapTime": 85.347
  },
  {
    "year": 2006,
    "session": "R",
    "driverId": "COU",
    "lapTime": 86.855
  },
  {
    "year": 2006,
    "session": "R",
    "driverId": "FIS",
    "lapTime": 85.353
  },
  {
    "year": 2006,
    "session": "R",
    "driverId": "HEI",
    "lapTime": 85.996
  },
  {
    "year": 2006,
    "session": "R",
    "driverId": "IDE",
    "lapTime": 91.032
  },
  {
    "year": 2006,
    "session": "R",
    "driverId": "KLI",
    "lapTime": 86.759
  },
  {
    "year": 2006,
    "session": "R",
    "driverId": "LIU",
    "lapTime": 85.679
  },
  {
    "year": 2006,
    "session": "R",
    "driverId": "MAS",
    "lapTime": 85.528
  },
  {
    "year": 2006,
    "session": "R",
    "driverId": "MON",
    "lapTime": 85.096
  },
  {
    "year": 2006,
    "session": "R",
    "driverId": "MSC",
    "lapTime": 84.624
  },
  {
    "year": 2006,
    "session": "R",
    "driverId": "RAI",
    "lapTime": 85.027
  },
  {
    "year": 2006,
    "session": "R",
    "driverId": "ROS",
    "lapTime": 86.418
  },
  {
    "year": 2006,
    "session": "R",
    "driverId": "SAT",
    "lapTime": 89.1
  },
  {
    "year": 2006,
    "session": "R",
    "driverId": "SCH",
    "lapTime": 85.316
  },
  {
    "year": 2006,
    "session": "R",
    "driverId": "SPE",
    "lapTime": 86.248
  },
  {
    "year": 2006,
    "session": "R",
    "driverId": "TMO",
    "lapTime": 87.16
  },
  {
    "year": 2006,
    "session": "R",
    "driverId": "TRU",
    "lapTime": 88.039
  },
  {
    "year": 2006,
    "session": "R",
    "driverId": "VIL",
    "lapTime": 85.438
  },
  {
    "year": 2006,
    "session": "R",
    "driverId": "WEB",
    "lapTime": 85.488
  },
  {
    "year": 2020,
    "session": "Q",
    "driverId": "ALB",
    "lapTime": 74.572
  },
  {
    "year": 2020,
    "session": "Q",
    "driverId": "BOT",
    "lapTime": 73.609
  },
  {
    "year": 2020,
    "session": "Q",
    "driverId": "GAS",
    "lapTime": 74.502
  },
  {
    "year": 2020,
    "session": "Q",
    "driverId": "GIO",
    "lapTime": 76.208
  },
  {
    "year": 2020,
    "session": "Q",
    "driverId": "GRO",
    "lapTime": 75.918
  },
  {
    "year": 2020,
    "session": "Q",
    "driverId": "HAM",
    "lapTime": 73.706
  },
  {
    "year": 2020,
    "session": "Q",
    "driverId": "KVY",
    "lapTime": 74.696
  },
  {
    "year": 2020,
    "session": "Q",
    "driverId": "LAT",
    "lapTime": 75.987
  },
  {
    "year": 2020,
    "session": "Q",
    "driverId": "LEC",
    "lapTime": 74.616
  },
  {
    "year": 2020,
    "session": "Q",
    "driverId": "MAG",
    "lapTime": 75.939
  },
  {
    "year": 2020,
    "session": "Q",
    "driverId": "NOR",
    "lapTime": 74.814
  },
  {
    "year": 2020,
    "session": "Q",
    "driverId": "OCO",
    "lapTime": 75.201
  },
  {
    "year": 2020,
    "session": "Q",
    "driverId": "PER",
    "lapTime": 75.061
  },
  {
    "year": 2020,
    "session": "Q",
    "driverId": "RAI",
    "lapTime": 75.953
  },
  {
    "year": 2020,
    "session": "Q",
    "driverId": "RIC",
    "lapTime": 74.52
  },
  {
    "year": 2020,
    "session": "Q",
    "driverId": "RUS",
    "lapTime": 75.323
  },
  {
    "year": 2020,
    "session": "Q",
    "driverId": "SAI",
    "lapTime": 74.911
  },
  {
    "year": 2020,
    "session": "Q",
    "driverId": "STR",
    "lapTime": 75.494
  },
  {
    "year": 2020,
    "session": "Q",
    "driverId": "VER",
    "lapTime": 74.176
  },
  {
    "year": 2020,
    "session": "Q",
    "driverId": "VET",
    "lapTime": 75.385
  },
  {
    "year": 2020,
    "session": "R",
    "driverId": "ALB",
    "lapTime": 76.177
  },
  {
    "year": 2020,
    "session": "R",
    "driverId": "BOT",
    "lapTime": 75.902
  },
  {
    "year": 2020,
    "session": "R",
    "driverId": "GAS",
    "lapTime": 80.403
  },
  {
    "year": 2020,
    "session": "R",
    "driverId": "GIO",
    "lapTime": 78.794
  },
  {
    "year": 2020,
    "session": "R",
    "driverId": "GRO",
    "lapTime": 78.822
  },
  {
    "year": 2020,
    "session": "R",
    "driverId": "HAM",
    "lapTime": 75.484
  },
  {
    "year": 2020,
    "session": "R",
    "driverId": "KVY",
    "lapTime": 77.666
  },
  {
    "year": 2020,
    "session": "R",
    "driverId": "LAT",
    "lapTime": 78.719
  },
  {
    "year": 2020,
    "session": "R",
    "driverId": "LEC",
    "lapTime": 78.173
  },
  {
    "year": 2020,
    "session": "R",
    "driverId": "MAG",
    "lapTime": 79.273
  },
  {
    "year": 2020,
    "session": "R",
    "driverId": "NOR",
    "lapTime": 78.069
  },
  {
    "year": 2020,
    "session": "R",
    "driverId": "OCO",
    "lapTime": 79.606
  },
  {
    "year": 2020,
    "session": "R",
    "driverId": "PER",
    "lapTime": 78.084
  },
  {
    "year": 2020,
    "session": "R",
    "driverId": "RAI",
    "lapTime": 78.088
  },
  {
    "year": 2020,
    "session": "R",
    "driverId": "RIC",
    "lapTime": 77.552
  },
  {
    "year": 2020,
    "session": "R",
    "driverId": "RUS",
    "lapTime": 78.811
  },
  {
    "year": 2020,
    "session": "R",
    "driverId": "SAI",
    "lapTime": 78.118
  },
  {
    "year": 2020,
    "session": "R",
    "driverId": "STR",
    "lapTime": 78.36
  },
  {
    "year": 2020,
    "session": "R",
    "driverId": "VER",
    "lapTime": 77.637
  },
  {
    "year": 2020,
    "session": "R",
    "driverId": "VET",
    "lapTime": 77.767
  },
  {
    "year": 2021,
    "session": "Q",
    "driverId": "ALO",
    "lapTime": 75.593
  },
  {
    "year": 2021,
    "session": "Q",
    "driverId": "BOT",
    "lapTime": 74.672
  },
  {
    "year": 2021,
    "session": "Q",
    "driverId": "GAS",
    "lapTime": 74.79
  },
  {
    "year": 2021,
    "session": "Q",
    "driverId": "GIO",
    "lapTime": 76.122
  },
  {
    "year": 2021,
    "session": "Q",
    "driverId": "HAM",
    "lapTime": 74.411
  },
  {
    "year": 2021,
    "session": "Q",
    "driverId": "LAT",
    "lapTime": 75.593
  },
  {
    "year": 2021,
    "session": "Q",
    "driverId": "LEC",
    "lapTime": 74.74
  },
  {
    "year": 2021,
    "session": "Q",
    "driverId": "MAZ",
    "lapTime": 76.797
  },
  {
    "year": 2021,
    "session": "Q",
    "driverId": "MSC",
    "lapTime": 76.279
  },
  {
    "year": 2021,
    "session": "Q",
    "driverId": "NOR",
    "lapTime": 74.718
  },
  {
    "year": 2021,
    "session": "Q",
    "driverId": "OCO",
    "lapTime": 75.117
  },
  {
    "year": 2021,
    "session": "Q",
    "driverId": "PER",
    "lapTime": 74.446
  },
  {
    "year": 2021,
    "session": "Q",
    "driverId": "RAI",
    "lapTime": 75.974
  },
  {
    "year": 2021,
    "session": "Q",
    "driverId": "RIC",
    "lapTime": 74.826
  },
  {
    "year": 2021,
    "session": "Q",
    "driverId": "RUS",
    "lapTime": 75.261
  },
  {
    "year": 2021,
    "session": "Q",
    "driverId": "SAI",
    "lapTime": 75.199
  },
  {
    "year": 2021,
    "session": "Q",
    "driverId": "STR",
    "lapTime": 75.138
  },
  {
    "year": 2021,
    "session": "Q",
    "driverId": "VER",
    "lapTime": 74.498
  },
  {
    "year": 2021,
    "session": "Q",
    "driverId": "VET",
    "lapTime": 75.394
  },
  {
    "year": 2021,
    "session": "R",
    "driverId": "ALO",
    "lapTime": 79.417
  },
  {
    "year": 2021,
    "session": "R",
    "driverId": "BOT",
    "lapTime": 88.485
  },
  {
    "year": 2021,
    "session": "R",
    "driverId": "GAS",
    "lapTime": 78.994
  },
  {
    "year": 2021,
    "session": "R",
    "driverId": "GIO",
    "lapTime": 79.47
  },
  {
    "year": 2021,
    "session": "R",
    "driverId": "HAM",
    "lapTime": 76.702
  },
  {
    "year": 2021,
    "session": "R",
    "driverId": "LEC",
    "lapTime": 78.379
  },
  {
    "year": 2021,
    "session": "R",
    "driverId": "MAZ",
    "lapTime": 80.402
  },
  {
    "year": 2021,
    "session": "R",
    "driverId": "MSC",
    "lapTime": 79.193
  },
  {
    "year": 2021,
    "session": "R",
    "driverId": "NOR",
    "lapTime": 78.259
  },
  {
    "year": 2021,
    "session": "R",
    "driverId": "OCO",
    "lapTime": 79.422
  },
  {
    "year": 2021,
    "session": "R",
    "driverId": "PER",
    "lapTime": 79.396
  },
  {
    "year": 2021,
    "session": "R",
    "driverId": "RAI",
    "lapTime": 78.353
  },
  {
    "year": 2021,
    "session": "R",
    "driverId": "RIC",
    "lapTime": 79.341
  },
  {
    "year": 2021,
    "session": "R",
    "driverId": "RUS",
    "lapTime": 86.543
  },
  {
    "year": 2021,
    "session": "R",
    "driverId": "SAI",
    "lapTime": 78.49
  },
  {
    "year": 2021,
    "session": "R",
    "driverId": "STR",
    "lapTime": 78.782
  },
  {
    "year": 2021,
    "session": "R",
    "driverId": "TSU",
    "lapTime": 78.334
  },
  {
    "year": 2021,
    "session": "R",
    "driverId": "VER",
    "lapTime": 77.524
  },
  {
    "year": 2021,
    "session": "R",
    "driverId": "VET",
    "lapTime": 79.074
  },
  {
    "year": 2022,
    "session": "Q",
    "driverId": "ALO",
    "lapTime": 79.595
  },
  {
    "year": 2022,
    "session": "Q",
    "driverId": "BOT",
    "lapTime": 80.192
  },
  {
    "year": 2022,
    "session": "Q",
    "driverId": "GAS",
    "lapTime": 80.732
  },
  {
    "year": 2022,
    "session": "Q",
    "driverId": "HAM",
    "lapTime": 80.47
  },
  {
    "year": 2022,
    "session": "Q",
    "driverId": "LAT",
    "lapTime": 81.971
  },
  {
    "year": 2022,
    "session": "Q",
    "driverId": "LEC",
    "lapTime": 78.796
  },
  {
    "year": 2022,
    "session": "Q",
    "driverId": "MAG",
    "lapTime": 79.902
  },
  {
    "year": 2022,
    "session": "Q",
    "driverId": "MSC",
    "lapTime": 80.422
  },
  {
    "year": 2022,
    "session": "Q",
    "driverId": "NOR",
    "lapTime": 79.294
  },
  {
    "year": 2022,
    "session": "Q",
    "driverId": "OCO",
    "lapTime": 82.338
  },
  {
    "year": 2022,
    "session": "Q",
    "driverId": "PER",
    "lapTime": 79.296
  },
  {
    "year": 2022,
    "session": "Q",
    "driverId": "RIC",
    "lapTime": 79.98
  },
  {
    "year": 2022,
    "session": "Q",
    "driverId": "RUS",
    "lapTime": 80.383
  },
  {
    "year": 2022,
    "session": "Q",
    "driverId": "SAI",
    "lapTime": 78.99
  },
  {
    "year": 2022,
    "session": "Q",
    "driverId": "STR",
    "lapTime": 80.342
  },
  {
    "year": 2022,
    "session": "Q",
    "driverId": "TSU",
    "lapTime": 80.474
  },
  {
    "year": 2022,
    "session": "Q",
    "driverId": "VER",
    "lapTime": 78.793
  },
  {
    "year": 2022,
    "session": "Q",
    "driverId": "VET",
    "lapTime": 79.957
  },
  {
    "year": 2022,
    "session": "Q",
    "driverId": "ZHO",
    "lapTime": 79.73
  },
  {
    "year": 2022,
    "session": "R",
    "driverId": "ALB",
    "lapTime": 81.757
  },
  {
    "year": 2022,
    "session": "R",
    "driverId": "ALO",
    "lapTime": 99.685
  },
  {
    "year": 2022,
    "session": "R",
    "driverId": "BOT",
    "lapTime": 80.758
  },
  {
    "year": 2022,
    "session": "R",
    "driverId": "GAS",
    "lapTime": 81.713
  },
  {
    "year": 2022,
    "session": "R",
    "driverId": "HAM",
    "lapTime": 81.419
  },
  {
    "year": 2022,
    "session": "R",
    "driverId": "LAT",
    "lapTime": 81.338
  },
  {
    "year": 2022,
    "session": "R",
    "driverId": "LEC",
    "lapTime": 78.574
  },
  {
    "year": 2022,
    "session": "R",
    "driverId": "MAG",
    "lapTime": 81.238
  },
  {
    "year": 2022,
    "session": "R",
    "driverId": "MSC",
    "lapTime": 78.999
  },
  {
    "year": 2022,
    "session": "R",
    "driverId": "NOR",
    "lapTime": 80.903
  },
  {
    "year": 2022,
    "session": "R",
    "driverId": "OCO",
    "lapTime": 81.887
  },
  {
    "year": 2022,
    "session": "R",
    "driverId": "PER",
    "lapTime": 78.949
  },
  {
    "year": 2022,
    "session": "R",
    "driverId": "RIC",
    "lapTime": 81.577
  },
  {
    "year": 2022,
    "session": "R",
    "driverId": "RUS",
    "lapTime": 80.962
  },
  {
    "year": 2022,
    "session": "R",
    "driverId": "STR",
    "lapTime": 81.75
  },
  {
    "year": 2022,
    "session": "R",
    "driverId": "TSU",
    "lapTime": 80.544
  },
  {
    "year": 2022,
    "session": "R",
    "driverId": "VER",
    "lapTime": 78.446
  },
  {
    "year": 2022,
    "session": "R",
    "driverId": "VET",
    "lapTime": 81.211
  },
  {
    "year": 2022,
    "session": "R",
    "driverId": "ZHO",
    "lapTime": 81.286
  },
  {
    "year": 2024,
    "session": "Q",
    "driverId": "ALB",
    "lapTime": 76.2
  },
  {
    "year": 2024,
    "session": "Q",
    "driverId": "ALO",
    "lapTime": 76.917
  },
  {
    "year": 2024,
    "session": "Q",
    "driverId": "BOT",
    "lapTime": 76.626
  },
  {
    "year": 2024,
    "session": "Q",
    "driverId": "GAS",
    "lapTime": 76.015
  },
  {
    "year": 2024,
    "session": "Q",
    "driverId": "HAM",
    "lapTime": 75.504
  },
  {
    "year": 2024,
    "session": "Q",
    "driverId": "HUL",
    "lapTime": 75.569
  },
  {
    "year": 2024,
    "session": "Q",
    "driverId": "LEC",
    "lapTime": 74.97
  },
  {
    "year": 2024,
    "session": "Q",
    "driverId": "MAG",
    "lapTime": 76.854
  },
  {
    "year": 2024,
    "session": "Q",
    "driverId": "NOR",
    "lapTime": 74.837
  },
  {
    "year": 2024,
    "session": "Q",
    "driverId": "OCO",
    "lapTime": 75.906
  },
  {
    "year": 2024,
    "session": "Q",
    "driverId": "PER",
    "lapTime": 75.706
  },
  {
    "year": 2024,
    "session": "Q",
    "driverId": "PIA",
    "lapTime": 74.82
  },
  {
    "year": 2024,
    "session": "Q",
    "driverId": "RIC",
    "lapTime": 75.674
  },
  {
    "year": 2024,
    "session": "Q",
    "driverId": "RUS",
    "lapTime": 75.234
  },
  {
    "year": 2024,
    "session": "Q",
    "driverId": "SAI",
    "lapTime": 75.233
  },
  {
    "year": 2024,
    "session": "Q",
    "driverId": "STR",
    "lapTime": 75.992
  },
  {
    "year": 2024,
    "session": "Q",
    "driverId": "TSU",
    "lapTime": 75.358
  },
  {
    "year": 2024,
    "session": "Q",
    "driverId": "VER",
    "lapTime": 74.746
  },
  {
    "year": 2024,
    "session": "Q",
    "driverId": "ZHO",
    "lapTime": 76.834
  },
  {
    "year": 2024,
    "session": "R",
    "driverId": "ALB",
    "lapTime": 81.274
  },
  {
    "year": 2024,
    "session": "R",
    "driverId": "ALO",
    "lapTime": 79.004
  },
  {
    "year": 2024,
    "session": "R",
    "driverId": "BOT",
    "lapTime": 81.455
  },
  {
    "year": 2024,
    "session": "R",
    "driverId": "GAS",
    "lapTime": 81.371
  },
  {
    "year": 2024,
    "session": "R",
    "driverId": "HAM",
    "lapTime": 80.331
  },
  {
    "year": 2024,
    "session": "R",
    "driverId": "HUL",
    "lapTime": 81.7
  },
  {
    "year": 2024,
    "session": "R",
    "driverId": "LEC",
    "lapTime": 79.935
  },
  {
    "year": 2024,
    "session": "R",
    "driverId": "MAG",
    "lapTime": 81.009
  },
  {
    "year": 2024,
    "session": "R",
    "driverId": "NOR",
    "lapTime": 79.994
  },
  {
    "year": 2024,
    "session": "R",
    "driverId": "OCO",
    "lapTime": 81.304
  },
  {
    "year": 2024,
    "session": "R",
    "driverId": "PER",
    "lapTime": 79.686
  },
  {
    "year": 2024,
    "session": "R",
    "driverId": "PIA",
    "lapTime": 79.907
  },
  {
    "year": 2024,
    "session": "R",
    "driverId": "RIC",
    "lapTime": 81.569
  },
  {
    "year": 2024,
    "session": "R",
    "driverId": "RUS",
    "lapTime": 78.589
  },
  {
    "year": 2024,
    "session": "R",
    "driverId": "SAI",
    "lapTime": 80.22
  },
  {
    "year": 2024,
    "session": "R",
    "driverId": "SAR",
    "lapTime": 81.229
  },
  {
    "year": 2024,
    "session": "R",
    "driverId": "STR",
    "lapTime": 80.57
  },
  {
    "year": 2024,
    "session": "R",
    "driverId": "TSU",
    "lapTime": 80.936
  },
  {
    "year": 2024,
    "session": "R",
    "driverId": "VER",
    "lapTime": 80.366
  },
  {
    "year": 2024,
    "session": "R",
    "driverId": "ZHO",
    "lapTime": 81.016
  }
]